rupy/__init__.py
rupy/bitview.py
rupy/buf.py
rupy/fields.py
rupy/hexdump.py
rupy/pretty.py
rupy/seq.py
rupy/stream.py
rupy-0.6.dist-info/LICENSE
rupy-0.6.dist-info/METADATA
rupy-0.6.dist-info/WHEEL
rupy-0.6.dist-info/top_level.txt
rupy-0.6.dist-info/RECORD
