Metadata-Version: 2.1
Name: rupy
Version: 0.6
Summary: Random useful python stuff
Home-page: https://github.com/yyogo/rupy,
Author: Jonathan Goren
Author-email: jonagn@gmail.com
License: MIT License,
Classifier: Programming Language :: Python :: 3
Classifier: License :: OSI Approved :: MIT License
Classifier: Operating System :: OS Independent
Classifier: Development Status :: 3 - Alpha
Classifier: Topic :: Utilities
Classifier: Topic :: Security
License-File: LICENSE
